README.md
setup.py
flask_yamli18n/__init__.py
flask_yamli18n.egg-info/PKG-INFO
flask_yamli18n.egg-info/SOURCES.txt
flask_yamli18n.egg-info/dependency_links.txt
flask_yamli18n.egg-info/not-zip-safe
flask_yamli18n.egg-info/requires.txt
flask_yamli18n.egg-info/top_level.txt